schedule/__init__.py
schedule/crontab.py
schedule/py.typed
schedule_cronjob-1.3.1.dist-info/AUTHORS.rst
schedule_cronjob-1.3.1.dist-info/LICENSE.txt
schedule_cronjob-1.3.1.dist-info/METADATA
schedule_cronjob-1.3.1.dist-info/WHEEL
schedule_cronjob-1.3.1.dist-info/top_level.txt
schedule_cronjob-1.3.1.dist-info/RECORD
