Metadata-Version: 2.1
Name: schedule-cronjob
Version: 1.3.1
Summary: Job scheduling for humans. With cronjob support.
Home-page: https://github.com/yusefmaali/schedule-cronjob
Download-URL: https://github.com/yusefmaali/schedule-cronjob/tarball/1.3.1
Author: Daniel Bader
Author-email: mail@dbader.org
Maintainer: Yusef Maali
Maintainer-email: contact@yusefmaali.net
License: MIT
Keywords: schedule,periodic,jobs,scheduling,clockwork,cron,scheduler,job scheduling,cronjob,cronjob scheduling
Classifier: Intended Audience :: Developers
Classifier: License :: OSI Approved :: MIT License
Classifier: Development Status :: 5 - Production/Stable
Classifier: Operating System :: OS Independent
Classifier: Programming Language :: Python
Classifier: Programming Language :: Python :: 3
Classifier: Programming Language :: Python :: 3.7
Classifier: Programming Language :: Python :: 3.8
Classifier: Programming Language :: Python :: 3.9
Classifier: Programming Language :: Python :: 3.10
Classifier: Programming Language :: Python :: 3.11
Classifier: Natural Language :: English
Requires-Python: >=3.7
License-File: LICENSE.txt
License-File: AUTHORS.rst
